function_analyser/__init__.py
function_analyser/__main__.py
function_analyser/config.yaml
function_analyser/main.py
function_analyser/missing_docstring.py
function_analyser/parse_function.py
function_analyser/statistics.py
function_analyser-0.0.15.dist-info/LICENSE.txt
function_analyser-0.0.15.dist-info/METADATA
function_analyser-0.0.15.dist-info/WHEEL
function_analyser-0.0.15.dist-info/top_level.txt
function_analyser-0.0.15.dist-info/RECORD
