Metadata-Version: 2.1
Name: function-analyser
Version: 0.0.15
Summary: Identify long functions to refactor with this function analyser
Author-email: Nicholas Hemley <nicholas.oliver.hemley@gmail.com>
Maintainer-email: Nicholas Hemley <nicholas.oliver.hemley@gmail.com>
License: Copyright 2023, Nicholas Hemley
Keywords: analysis,static,refactoring,code,smells
Classifier: Development Status :: 3 - Alpha
Classifier: Intended Audience :: Developers
Classifier: Topic :: Software Development :: Build Tools
Classifier: License :: OSI Approved :: MIT License
Classifier: Programming Language :: Python :: 3
Classifier: Programming Language :: Python :: 3.7
Classifier: Programming Language :: Python :: 3.8
Classifier: Programming Language :: Python :: 3.9
Classifier: Programming Language :: Python :: 3.10
Classifier: Programming Language :: Python :: 3.11
Classifier: Programming Language :: Python :: 3 :: Only
Requires-Python: >=3.7
License-File: LICENSE.txt
Requires-Dist: pandas
Requires-Dist: numpy
Provides-Extra: dev
Requires-Dist: check-manifest ; extra == 'dev'
Provides-Extra: test
Requires-Dist: coverage ; extra == 'test'
